pve_cloud_schemas/_version.py
pve_cloud_schemas/validate.py
pve_cloud_schemas/definitions/kubespray_inv_schema.yaml
pve_cloud_schemas/definitions/lxc_inv_schema.yaml
pve_cloud_schemas/definitions/pve_cloud_inv_schema.yaml
pve_cloud_schemas/definitions/qemu_inv_schema.yaml
pve_cloud_schemas/definitions/qemu_schema_base.yaml
pve_cloud_schemas/definitions/vm_schema_base.yaml
pve_cloud_schemas/extensions/setup_bind_schema_ext.yaml
pve_cloud_schemas/extensions/setup_ceph_kea_schema_ext.yaml
pve_cloud_schemas/extensions/setup_haproxy_schema_ext.yaml
pve_cloud_schemas/extensions/setup_kea_schema_ext.yaml
pve_cloud_schemas-0.4.8.dist-info/licenses/LICENSE.md
pve_cloud_schemas-0.4.8.dist-info/METADATA
pve_cloud_schemas-0.4.8.dist-info/WHEEL
pve_cloud_schemas-0.4.8.dist-info/entry_points.txt
pve_cloud_schemas-0.4.8.dist-info/top_level.txt
pve_cloud_schemas-0.4.8.dist-info/RECORD
