Metadata-Version: 2.4
Name: pve-cloud-schemas
Version: 0.4.8
Author-email: Tobias Huebner <tobias.huebner@vmzberlin.com>
License-Expression: GPL-3.0-or-later
License-File: LICENSE.md
Requires-Dist: PyYAML==6.0.3
Requires-Dist: jsonschema==4.26.0
Dynamic: license-file
